{
    "Vue Single File Component": {
		"prefix": "vbase",
		"body": [
			"<template>",
			"\t<div>",
			"",
			"\t</div>",
			"</template>",
			"",
			"<script>",
			"\texport default {",
			"\t\t${0}",
			"\t}",
			"</script>",
			"",
			"<style scoped>",
			"",
			"</style>"
		],
		"description": "Base for Vue File"
	},
    "template": {
        "prefix": "template",
        "body": [
            "<template>",
            "\t$1",
            "</template>"
        ],
        "description": "template element"
    },
    "script": {
        "prefix": "script",
        "body": [
            "<script>",
            "\t$1",
            "</script>"
        ],
        "description": "script element"
    },
    "styleLang": {
        "prefix": "styleLang",
        "body": [
            "<style lang=\"$1\">",
            "\t$0",
            "</style>"
        ],
        "description": "style element with lang attribute"
    }
}
